carlos_quinto/__init__.py
carlos_quinto/carlos_quinto.py
prueba_temporal-0.1.0.dist-info/DESCRIPTION.rst
prueba_temporal-0.1.0.dist-info/METADATA
prueba_temporal-0.1.0.dist-info/RECORD
prueba_temporal-0.1.0.dist-info/WHEEL
prueba_temporal-0.1.0.dist-info/metadata.json
prueba_temporal-0.1.0.dist-info/top_level.txt
