Metadata-Version: 2.0
Name: prueba-temporal
Version: 0.1.0
Summary: Descripción corta del proyecto.
Home-page: https://github.com/datosgobar/prueba-temporal
Author: Datos Argentina
Author-email: datos@modernizacion.gob.ar
License: MIT license
Keywords: carlos_quinto
Platform: UNKNOWN
Classifier: Development Status :: 2 - Pre-Alpha
Classifier: Intended Audience :: Developers
Classifier: License :: OSI Approved :: MIT License
Classifier: Natural Language :: English
Classifier: Programming Language :: Python :: 2
Classifier: Programming Language :: Python :: 2.7
Requires-Dist: arrow
